python_cmc/__init__.py
python_cmc/cmc.py
python_cmc/crmf.py
python_cmc/py.typed
python_cmc-1.22.dist-info/LICENSE
python_cmc-1.22.dist-info/WHEEL
python_cmc-1.22.dist-info/METADATA
python_cmc-1.22.dist-info/RECORD
