Metadata-Version: 2.1
Name: python_cmc
Version: 1.22
Summary: Python CMC
License: MIT
Keywords: x509,cmc,crmf
Author: Victor Näslund
Author-email: victor@sunet.se
Requires-Python: >=3.7
Requires-Dist: asn1crypto>=1.4.0
